{"expireTime":9007200892527327000,"key":"fa0ea6a45fe33e4874208243b572e871","val":{"name":"IMAGE_PROCESSING","inputPaths":["/Users/dave/gatsby-strapi/frontend/.cache/caches/gatsby-source-strapi/f9855c70bce8681861127e6e00c083f1/favicon_0fa78dae31.png"],"outputDir":"/Users/dave/gatsby-strapi/frontend/public/static/ae6afb4b615b66cddf6a20b5a937e384","args":{"isLazy":false,"operations":[{"outputPath":"22867/favicon_0fa78dae31.png","args":{"height":8,"width":8,"cropFocus":17,"toFormat":"png","fit":"cover"}},{"outputPath":"7961d/favicon_0fa78dae31.png","args":{"height":15,"width":15,"cropFocus":17,"toFormat":"png","fit":"cover"}},{"outputPath":"53973/favicon_0fa78dae31.png","args":{"height":30,"width":30,"cropFocus":17,"toFormat":"png","fit":"cover"}},{"outputPath":"7ab40/favicon_0fa78dae31.png","args":{"height":60,"width":60,"cropFocus":17,"toFormat":"png","fit":"cover"}}],"pluginOptions":{"base64Width":20,"forceBase64Format":"","useMozJpeg":false,"stripMetadata":true,"lazyImageGeneration":true,"defaultQuality":50,"failOnError":true,"plugins":[]}}}}